JMatuszczakL/__init__.py
JMatuszczakL-1.0.6.dist-info/METADATA
JMatuszczakL-1.0.6.dist-info/WHEEL
JMatuszczakL-1.0.6.dist-info/top_level.txt
JMatuszczakL-1.0.6.dist-info/RECORD
